lightlogo/__init__.py
lightlogo/annotation3d.py
lightlogo/play3D.py
lightlogo/surface3D.py
lightlogo/text3D.py
lightlogo/tur.png
lightlogo/turtle3D.py
lightlogo/world3D.py
lightlogo/__pycache__/__init__.cpython-39.pyc
lightlogo/__pycache__/annotation3d.cpython-39.pyc
lightlogo/__pycache__/play3D.cpython-39.pyc
lightlogo/__pycache__/surface3D.cpython-39.pyc
lightlogo/__pycache__/text3D.cpython-39.pyc
lightlogo/__pycache__/turtle3D.cpython-39.pyc
lightlogo/__pycache__/world3D.cpython-39.pyc
LightLogo-0.0.1a1.dist-info/LICENSE
LightLogo-0.0.1a1.dist-info/METADATA
LightLogo-0.0.1a1.dist-info/WHEEL
LightLogo-0.0.1a1.dist-info/top_level.txt
LightLogo-0.0.1a1.dist-info/RECORD
