Metadata-Version: 2.1
Name: LightLogo
Version: 0.0.1a1
Summary: A simple, lightweight and powerful 3D agent-based simulation toolkit with Logo
Home-page: https://github.com/dhchenx/LightLogo
Author: Donghua Chen
Author-email: douglaschan@126.com
License: BSD-3
Project-URL: Bug Reports, https://github.com/dhchenx/LightLogo/issues
Project-URL: Source, https://github.com/dhchenx/LightLogo
Keywords: logo,lightlogo,llogo,agent-based modeling,simulation,turtle in 3D
Platform: UNKNOWN
Classifier: Development Status :: 5 - Production/Stable
Classifier: Intended Audience :: Developers
Classifier: Topic :: Software Development :: Build Tools
Classifier: License :: OSI Approved :: MIT License
Classifier: Programming Language :: Python :: 3
Classifier: Programming Language :: Python :: 3.6
Classifier: Programming Language :: Python :: 3.7
Classifier: Programming Language :: Python :: 3.8
Classifier: Programming Language :: Python :: 3.9
Classifier: Programming Language :: Python :: 3 :: Only
Requires-Python: >=3.6, <4
License-File: LICENSE
Requires-Dist: matplotlib
Provides-Extra: dev
Requires-Dist: check-manifest ; extra == 'dev'
Provides-Extra: test
Requires-Dist: coverage ; extra == 'test'
